AUTHORS.rst
CONTRIBUTING.rst
HISTORY.rst
LICENSE
MANIFEST.in
README.rst
setup.cfg
setup.py
acme_challenge/__init__.py
acme_challenge/apps.py
acme_challenge/apps_settings.py
acme_challenge/models.py
acme_challenge/urls.py
acme_challenge/views.py
django_acme.egg-info/PKG-INFO
django_acme.egg-info/SOURCES.txt
django_acme.egg-info/dependency_links.txt
django_acme.egg-info/not-zip-safe
django_acme.egg-info/top_level.txt