Metadata-Version: 1.1
Name: django-acme
Version: 0.2.1
Summary: A re-usable Django app to quickly deploy a page for the ACME challenge
Home-page: https://github.com/browniebroke/django-acme
Author: Bruno Alla
Author-email: alla.brunoo@gmail.com
License: MIT
Keywords: django-acme
Platform: UNKNOWN
Classifier: Development Status :: 3 - Alpha
Classifier: Framework :: Django
Classifier: Framework :: Django :: 1.8
Classifier: Framework :: Django :: 1.9
Classifier: Framework :: Django :: 1.10
Classifier: Intended Audience :: Developers
Classifier: License :: OSI Approved :: BSD License
Classifier: Natural Language :: English
Classifier: Programming Language :: Python :: 2
Classifier: Programming Language :: Python :: 2.7
Classifier: Programming Language :: Python :: 3
Classifier: Programming Language :: Python :: 3.3
Classifier: Programming Language :: Python :: 3.4
Classifier: Programming Language :: Python :: 3.5
